LICENSE.txt
MANIFEST.in
README.md
pyproject.toml
setup.cfg
setup.py
src/igrf/CMakeLists.txt
src/igrf/__init__.py
src/igrf/__main__.py
src/igrf/base.py
src/igrf/plots.py
src/igrf/utils.py
src/igrf.egg-info/PKG-INFO
src/igrf.egg-info/SOURCES.txt
src/igrf.egg-info/dependency_links.txt
src/igrf.egg-info/entry_points.txt
src/igrf.egg-info/not-zip-safe
src/igrf.egg-info/requires.txt
src/igrf.egg-info/top_level.txt
src/igrf/fortran/igrf13.f
src/igrf/fortran/igrf13_driver.f90