Metadata-Version: 2.1
Name: igrf
Version: 13.0.2
Summary: IGRF13, IGRF12, IGRF11 models with simple object-oriented Python interface.
Home-page: https://github.com/space-physics/igrf
Author: Michael Hirsch, Ph.D.
Author-email: scivision@users.noreply.github.com
License: UNKNOWN
Keywords: geomagnetic,igrf
Platform: UNKNOWN
Classifier: Development Status :: 5 - Production/Stable
Classifier: Environment :: Console
Classifier: Intended Audience :: Science/Research
Classifier: Operating System :: OS Independent
Classifier: Programming Language :: Fortran
Classifier: Programming Language :: Python :: 3
Classifier: Topic :: Scientific/Engineering :: Atmospheric Science
Requires-Python: >=3.7
Provides-Extra: tests
Provides-Extra: lint
Provides-Extra: plot
